my_first_library/__init__.py
my_first_library/common_functions.py
my_first_library/db_functions.py
my_first_lib-0.1.dist-info/METADATA
my_first_lib-0.1.dist-info/WHEEL
my_first_lib-0.1.dist-info/top_level.txt
my_first_lib-0.1.dist-info/RECORD
