Metadata-Version: 2.1
Name: my-first-lib
Version: 0.1
Summary: This  is very useful package
Author: me
Author-email: some@email.com
